__init__.py
app.py
targets.py
variables.py
tests/test_app.py
glabvars-0.2.0.dist-info/LICENSE
glabvars-0.2.0.dist-info/METADATA
glabvars-0.2.0.dist-info/WHEEL
glabvars-0.2.0.dist-info/entry_points.txt
glabvars-0.2.0.dist-info/top_level.txt
glabvars-0.2.0.dist-info/RECORD
