Metadata-Version: 2.1
Name: glabvars
Version: 0.2.0
Summary: A Python wrapper for retrieving Gitlab CI/CD variables
Author-email: Wouter Donders <wouter@42analytics.eu>
License: BSD 3-Clause License
Project-URL: Homepage, https://42analytics.eu
Project-URL: Documentations, https://gitlab.com/42analytics1/public/glabvars
Project-URL: Source, https://gitlab.com/42analytics1/public/glabvars
Project-URL: Download, https://gitlab.com/42analytics1/public/glabvars/-/packages
Project-URL: Tracker, https://gitlab.com/42analytics1/public/glabvars/-/issues
Classifier: Development Status :: 4 - Beta
Classifier: Natural Language :: English
Classifier: Operating System :: OS Independent
Classifier: Programming Language :: Python
Classifier: Programming Language :: Python :: 3.9
Classifier: Programming Language :: Python :: 3.10
Classifier: Programming Language :: Python :: 3.11
Classifier: Programming Language :: Python :: 3.12
Classifier: License :: OSI Approved :: BSD License
Requires-Python: >=3.9
License-File: LICENSE
Requires-Dist: pydantic (>=1.10.7)
